gig/__init__.py
gig/lib.py
gig/settings.py
gig_lib-1.0.0.dist-info/METADATA
gig_lib-1.0.0.dist-info/WHEEL
gig_lib-1.0.0.dist-info/top_level.txt
gig_lib-1.0.0.dist-info/RECORD
