Metadata-Version: 2.4
Name: gig-lib
Version: 1.0.0
Summary: Dependencias FastAPI para JWT y roles GIG
Author: Juan Malo
License-Expression: MIT
Requires-Python: >=3.12
Requires-Dist: fastapi==0.116.1
Requires-Dist: httpx==0.28.1
Requires-Dist: PyJWT==2.10.1
Requires-Dist: cryptography<51,>=42
Requires-Dist: pydantic==2.11.7
Requires-Dist: pydantic-settings==2.10.1
Requires-Dist: starlette==0.47.2
Requires-Dist: python-dotenv==1.1.1
Requires-Dist: uvicorn==0.35
